vexylicon/__init__.py
vexylicon/__version__.py
vexylicon/cli.py
vexylicon/core.py
vexylicon/vexylicon.py
vexylicon/assets/best_base.png
vexylicon/assets/best_base.svg
vexylicon/assets/themes/default.json
vexylicon/utils/__init__.py
vexylicon/utils/path_tools.py
vexylicon/utils/svg_processor.py
vexylicon/utils/theme_loader.py
vexylicon-1.4.3.dist-info/METADATA
vexylicon-1.4.3.dist-info/WHEEL
vexylicon-1.4.3.dist-info/entry_points.txt
vexylicon-1.4.3.dist-info/licenses/LICENSE
vexylicon-1.4.3.dist-info/RECORD
